MANIFEST.in
README.md
setup.py
paws/__init__.py
paws/cli.py
paws/compat.py
paws/constants.py
paws/core.py
paws/exceptions.py
paws/helpers.py
paws/main.py
paws/version.txt
paws/lib/__init__.py
paws/lib/remote.py
paws/lib/windows.py
paws/providers/__init__.py
paws/providers/libvirt_kvm.py
paws/providers/openstack.py
paws/tasks/__init__.py
paws/tasks/action.py
paws/tasks/configure.py
paws/tasks/group.py
paws/tasks/winsetup.py
paws_cli.egg-info/PKG-INFO
paws_cli.egg-info/SOURCES.txt
paws_cli.egg-info/dependency_links.txt
paws_cli.egg-info/entry_points.txt
paws_cli.egg-info/not-zip-safe
paws_cli.egg-info/requires.txt
paws_cli.egg-info/top_level.txt