Metadata-Version: 2.1
Name: paws-cli
Version: 0.6.0
Summary: A tool used to provision Windows systems and configure Windows services.
Home-page: https://rhpit.github.io/paws/
Author: Eduardo Cerqueira,Ryan Williams
Author-email: eduardomcerqueira@gmail.com,rwilliams5262@gmail.com
Maintainer: Eduardo Cerqueira,Ryan Williams
Maintainer-email: eduardomcerqueira@gmail.com,rwilliams5262@gmail.com
License: GPL
Keywords: Provision Automation Windows Quality Assurance Tests Hybrid
Platform: RHEL >= 7.2 Fedora >= 24 CentOS >= 7.2
Classifier: Development Status :: 5 - Production/Stable
Classifier: License :: OSI Approved :: GNU General Public License v3 (GPLv3)
Classifier: Programming Language :: Python :: 2.7
Classifier: Programming Language :: Python :: 3.6
Classifier: Topic :: Software Development :: Quality Assurance
Provides-Extra: libvirt
